html_table_reader/__init__.py
html_table_reader/parser_html.py
html_table_reader-0.0.2.dist-info/METADATA
html_table_reader-0.0.2.dist-info/WHEEL
html_table_reader-0.0.2.dist-info/licenses/LICENSE
html_table_reader-0.0.2.dist-info/RECORD
